<Experiment>
<Problem name = 'DTLZ1_19_15'>
<Algorithm name = 'GALE'>
<Run id = '1'>
<Summary>
<NumEvals>108</NumEvals>
<RunTime>4.65341997147</RunTime>
<IBD>0.957120321697</IBD>
<IBS>0.00555616935732</IBS>
<f1>7.23813258862e-05</f1>
<f2>4.6990914475e-05</f2>
<f3>1.37844640615e-06</f3>
<f4>0.000118464857591</f4>
<f5>0.000793989523163</f5>
<f6>0.000357413727229</f6>
<f7>0.000256380329876</f7>
<f8>0.00340933865896</f8>
<f9>0.000715429879869</f9>
<f10>0.0510073084768</f10>
<f11>0.173987986262</f11>
<f12>2.87749483473</f12>
<f13>6.77060503744</f13>
<f14>12.5165109114</f14>
<f15>146.508712877</f15>
</Summary></Run>
</Algorithm>
<Algorithm name = 'NSGAII'>
<Run id = '1'>
<Summary>
<NumEvals>0</NumEvals>
<RunTime>3.66768097878</RunTime>
<IBD>1.0</IBD>
<IBS>0</IBS>
<f1>0</f1>
<f2>0</f2>
<f3>0</f3>
<f4>0</f4>
<f5>0</f5>
<f6>0</f6>
<f7>0</f7>
<f8>0</f8>
<f9>0</f9>
<f10>0</f10>
<f11>0</f11>
<f12>0</f12>
<f13>0</f13>
<f14>0</f14>
<f15>0</f15>
</Summary></Run>
</Algorithm>
<Algorithm name = 'SPEA2'>
<Run id = '1'>
<Summary>
<NumEvals>0</NumEvals>
<RunTime>58.314622879</RunTime>
<IBD>1.0</IBD>
<IBS>0</IBS>
<f1>0</f1>
<f2>0</f2>
<f3>0</f3>
<f4>0</f4>
<f5>0</f5>
<f6>0</f6>
<f7>0</f7>
<f8>0</f8>
<f9>0</f9>
<f10>0</f10>
<f11>0</f11>
<f12>0</f12>
<f13>0</f13>
<f14>0</f14>
<f15>0</f15>
</Summary></Run>
</Algorithm>
<Algorithm name = 'DE'>
<Run id = '1'>
<Summary>
<NumEvals>3400</NumEvals>
<RunTime>3.46954488754</RunTime>
<IBD>0.94788465772</IBD>
<IBS>0.00142846062424</IBS>
<f1>0.0</f1>
<f2>0.0</f2>
<f3>0.0</f3>
<f4>0.0</f4>
<f5>0.0</f5>
<f6>0.0</f6>
<f7>0.0</f7>
<f8>0.0</f8>
<f9>0.0</f9>
<f10>0.0</f10>
<f11>0.0</f11>
<f12>0.0</f12>
<f13>0.0</f13>
<f14>0.0</f14>
<f15>31.8221902894</f15>
</Summary></Run>
</Algorithm>
<Algorithm name = 'ANYWHERE'>
<Run id = '1'>
<Summary>
<NumEvals>240</NumEvals>
<RunTime>39.9637880325</RunTime>
<IBD>0.940624216388</IBD>
<IBS>0.000471396314179</IBS>
<f1>0.0</f1>
<f2>0.0</f2>
<f3>0.0</f3>
<f4>0.0</f4>
<f5>0.0</f5>
<f6>0.0</f6>
<f7>0.0</f7>
<f8>0.0</f8>
<f9>0.0</f9>
<f10>0.0</f10>
<f11>0.0</f11>
<f12>0.0</f12>
<f13>0.0</f13>
<f14>0.0</f14>
<f15>63.0</f15>
</Summary></Run>
</Algorithm>
</Problem>
</Experiment>
